trepro-1.0.1.dist-info/METADATA
trepro-1.0.1.dist-info/WHEEL
trepro-1.0.1.dist-info/entry_points.txt
trepro/__init__.py
trepro/matplotlib.py
trepro-1.0.1.dist-info/RECORD
