Metadata-Version: 2.1
Name: trepro
Version: 1.0.1
Summary: Towards better reproductions, less effort.
Author-Email: Muxuan Li <InEase28@gmail.com>
License: MIT
Requires-Python: >=3.10
